Qbluetoothctl_helper.py
Qbluetoothctl_helper-0.0.2.dist-info/LICENSE
Qbluetoothctl_helper-0.0.2.dist-info/METADATA
Qbluetoothctl_helper-0.0.2.dist-info/WHEEL
Qbluetoothctl_helper-0.0.2.dist-info/top_level.txt
Qbluetoothctl_helper-0.0.2.dist-info/RECORD
