Metadata-Version: 2.1
Name: Qbluetoothctl_helper
Version: 0.0.2
Summary: Python bluetoothctl helper for QT.
Home-page: https://github.com/uutzinger/Qbluetoothctl_helper
Author: Urs Utzinger
Author-email: uutzinger@gmail.com
License: MIT
Keywords: bluetooth,bluetoothctl,Qt,pyQt
Classifier: Development Status :: 4 - Beta
Classifier: Intended Audience :: Developers
Classifier: Topic :: Software Development :: Libraries :: Python Modules
Classifier: License :: OSI Approved :: MIT License
Classifier: Programming Language :: Python :: 3
Requires-Python: >=3.6
License-File: LICENSE
Provides-Extra: pyqt5
Requires-Dist: PyQt5>=5.15; extra == "pyqt5"
Provides-Extra: pyqt6
Requires-Dist: PyQt6>=6.0; extra == "pyqt6"
